Workbook

Sheet Raw_Data
A1: Customer_ID | B1: Revenue | C1: Cost_to_Serve | D1: Orders | E1: Return_Rate | F1: Return_Rate_Clean | G1: Support_Tickets | H1: Tenure_Months
A2: C001 | B2: 2658 | C2: 21973 | D2: 22 | E2: 0.22 | F2: =IF(E2>1, E2/100, E2) -> 0.22 | G2: 16 | H2: 23
A3: C002 | B3: 5103 | C3: 14484 | D3: 1 | E3: 15 | F3: =IF(E3>1, E3/100, E3) -> 0.15 | G3: 18 | H3: 14
A4: C003 | B4: 25079 | C4: 27280 | D4: 11 | E4: 0.18 | F4: =IF(E4>1, E4/100, E4) -> 0.18 | G4: 16 | H4: 56
A5: C004 | B5: 16960 | C5: 26875 | D5: 12 | E5: 0.21 | F5: =IF(E5>1, E5/100, E5) -> 0.21 | G5: 20 | H5: 10
A6: C005 | B6: 30841 | C6: 7986 | D6: 2 | E6: 0.12 | F6: =IF(E6>1, E6/100, E6) -> 0.12 | G6: 5 | H6: 9
A7: C006 | B7: 25139 | C7: 19876 | D7: 30 | E7: 12 | F7: =IF(E7>1, E7/100, E7) -> 0.12 | G7: 15 | H7: 53
A8: C007 | B8: 11116 | C8: 10808 | D8: 12 | E8: 0.25 | F8: =IF(E8>1, E8/100, E8) -> 0.25 | G8: 3 | H8: 11
A9: C008 | B9: 44869 | C9: 16868 | D9: 22 | E9: 0.24 | F9: =IF(E9>1, E9/100, E9) -> 0.24 | G9: 3 | H9: 38
A10: C009 | B10: 40105 | C10: 2256 | D10: 6 | E10: 0.25 | F10: =IF(E10>1, E10/100, E10) -> 0.25 | G10: 20 | H10: 57
A11: C010 | B11: 48507 | C11: 7943 | D11: 20 | E11: 0.17 | F11: =IF(E11>1, E11/100, E11) -> 0.17 | G11: 6 | H11: 39
A12: C011 | B12: 12530 | C12: 23509 | D12: 4 | E12: 0.3 | F12: =IF(E12>1, E12/100, E12) -> 0.3 | G12: 16 | H12: 58
A13: C012 | B13: 13702 | C13: 24076 | D13: 6 | E13: 6 | F13: =IF(E13>1, E13/100, E13) -> 0.06 | G13: 11 | H13: 2
... A30: C029 | B30: 33508 | C30: 7252 | D30: 27 | E30: 3 | F30: =IF(E30>1, E30/100, E30) -> 0.03 | G30: 14 | H30: 16
A31: C030 | B31: 31918 | D31: 9 | E31: 24 | F31: =IF(E31>1, E31/100, E31) -> 0.24 | G31: 20 | H31: 55
A32: C031 | B32: 21796 | C32: 24046 | D32: 20 | E32: 15 | F32: =IF(E32>1, E32/100, E32) -> 0.15 | G32: 18 | H32: 54
A33: C032 | B33: 49521 | C33: 19342 | D33: 5 | E33: 0.21 | F33: =IF(E33>1, E33/100, E33) -> 0.21 | G33: 8 | H33: 60
A34: C033 | B34: 24992 | C34: 6860 | D34: 25 | E34: 15 | F34: =IF(E34>1, E34/100, E34) -> 0.15 | G34: 15 | H34: 65
A35: C034 | B35: 14168 | C35: 2237 | D35: 6 | E35: 0.25 | F35: =IF(E35>1, E35/100, E35) -> 0.25 | G35: 3 | H35: 60
A36: C035 | B36: 13475 | C36: 3293 | D36: 9 | E36: 0.29 | F36: =IF(E36>1, E36/100, E36) -> 0.29 | G36: 17 | H36: 8
A37: C036 | B37: 29892 | C37: 28329 | D37: 14 | E37: 8 | F37: =IF(E37>1, E37/100, E37) -> 0.08 | G37: 2 | H37: 67
A38: C037 | B38: 10507 | C38: 28524 | D38: 20 | E38: 23 | F38: =IF(E38>1, E38/100, E38) -> 0.23 | G38: 3 | H38: 30
A39: C038 | B39: 44476 | C39: 8811 | D39: 8 | E39: 0.26 | F39: =IF(E39>1, E39/100, E39) -> 0.26 | G39: 10 | H39: 62
A40: C039 | B40: 17860 | C40: 23935 | D40: 26 | E40: 0.05 | F40: =IF(E40>1, E40/100, E40) -> 0.05 | G40: 16 | H40: 29
A41: C040 | B41: 16645 | C41: 29691 | D41: 8 | E41: 30 | F41: =IF(E41>1, E41/100, E41) -> 0.3 | G41: 13 | H41: 67
A42: C041 | B42: 8465 | C42: 27589 | D42: 6 | E42: 0.06 | F42: =IF(E42>1, E42/100, E42) -> 0.06 | G42: 1 | H42: 34
A43: C042 | B43: 43908 | C43: 24510 | D43: 25 | E43: 17 | F43: =IF(E43>1, E43/100, E43) -> 0.17 | G43: 19 | H43: 72
... A47: C046 | B47: 37702 | C47: 5541 | D47: 17 | E47: 8 | F47: =IF(E47>1, E47/100, E47) -> 0.08 | G47: 4 | H47: 52
A48: C047 | B48: 15213 | D48: 11 | E48: 0.05 | F48: =IF(E48>1, E48/100, E48) -> 0.05 | G48: 0 | H48: 69
A49: C048 | B49: 38465 | D49: 2 | E49: 25 | F49: =IF(E49>1, E49/100, E49) -> 0.25 | G49: 0 | H49: 12
A50: C049 | B50: 40964 | C50: 7316 | D50: 27 | E50: 0.3 | F50: =IF(E50>1, E50/100, E50) -> 0.3 | G50: 15 | H50: 45
A51: C050 | B51: 3354 | C51: 26453 | D51: 5 | E51: 10 | F51: =IF(E51>1, E51/100, E51) -> 0.1 | G51: 2 | H51: 55
A52: C051 | B52: 39754 | C52: 17071 | D52: 7 | E52: 0.19 | F52: =IF(E52>1, E52/100, E52) -> 0.19 | G52: 10 | H52: 65
A53: C052 | B53: 9655 | C53: 9733 | D53: 24 | E53: 0.13 | F53: =IF(E53>1, E53/100, E53) -> 0.13 | G53: 2 | H53: 46
A54: C053 | B54: 14600 | C54: 13535 | D54: 17 | E54: 13 | F54: =IF(E54>1, E54/100, E54) -> 0.13 | G54: 16 | H54: 14
A55: C054 | B55: 43298 | C55: 7241 | D55: 22 | E55: 3 | F55: =IF(E55>1, E55/100, E55) -> 0.03 | G55: 18 | H55: 30
A56: C055 | B56: 20624 | C56: 26135 | D56: 26 | E56: 0.18 | F56: =IF(E56>1, E56/100, E56) -> 0.18 | G56: 20 | H56: 42
A57: C056 | B57: 24598 | C57: 8860 | D57: 22 | E57: 19 | F57: =IF(E57>1, E57/100, E57) -> 0.19 | G57: 20 | H57: 35
A58: C057 | B58: 30928 | C58: 11129 | D58: 15 | E58: 30 | F58: =IF(E58>1, E58/100, E58) -> 0.3 | G58: 19 | H58: 56
A59: C058 | B59: 5161 | D59: 25 | E59: 28 | F59: =IF(E59>1, E59/100, E59) -> 0.28 | G59: 9 | H59: 48
A60: C059 | B60: 44453 | C60: 11062 | D60: 15 | E60: 0.02 | F60: =IF(E60>1, E60/100, E60) -> 0.02 | G60: 8 | H60: 22
A61: C060 | B61: 30775 | C61: 17693 | D61: 9 | E61: 0.17 | F61: =IF(E61>1, E61/100, E61) -> 0.17 | G61: 8 | H61: 18
A62: C061 | B62: 19789 | C62: 6752 | D62: 17 | E62: 10 | F62: =IF(E62>1, E62/100, E62) -> 0.1 | G62: 16 | H62: 4
A63: C062 | B63: 43255 | C63: 14529 | D63: 14 | E63: 20 | F63: =IF(E63>1, E63/100, E63) -> 0.2 | G63: 19 | H63: 12
A64: C063 | B64: 4506 | C64: 21797 | D64: 28 | E64: 0.17 | F64: =IF(E64>1, E64/100, E64) -> 0.17 | G64: 19 | H64: 35
A65: C064 | B65: 22342 | C65: 21828 | D65: 10 | E65: 0.1 | F65: =IF(E65>1, E65/100, E65) -> 0.1 | G65: 5 | H65: 4
A66: C065 | B66: 37720 | C66: 19960 | D66: 4 | E66: 22 | F66: =IF(E66>1, E66/100, E66) -> 0.22 | G66: 19 | H66: 41
A67: C066 | B67: 30383 | C67: 15094 | D67: 17 | E67: 0.23 | F67: =IF(E67>1, E67/100, E67) -> 0.23 | G67: 14 | H67: 28
A68: C067 | B68: 9858 | C68: 3881 | D68: 1 | E68: 9 | F68: =IF(E68>1, E68/100, E68) -> 0.09 | G68: 19 | H68: 63
A69: C068 | B69: 48100 | C69: 27774 | D69: 17 | E69: 0.02 | F69: =IF(E69>1, E69/100, E69) -> 0.02 | G69: 7 | H69: 44
A70: C069 | B70: 21859 | C70: 19192 | D70: 1 | E70: 0.19 | F70: =IF(E70>1, E70/100, E70) -> 0.19 | G70: 13 | H70: 6
A71: C070 | B71: 45655 | C71: 25708 | D71: 26 | E71: 0.17 | F71: =IF(E71>1, E71/100, E71) -> 0.17 | G71: 13 | H71: 21
... A75: C074 | B75: 14069 | C75: 13970 | D75: 26 | E75: 20 | F75: =IF(E75>1, E75/100, E75) -> 0.2 | G75: 11 | H75: 20
A76: C075 | B76: 49591 | D76: 26 | E76: 0.15 | F76: =IF(E76>1, E76/100, E76) -> 0.15 | G76: 0 | H76: 51
A77: C076 | B77: 27050 | C77: 17324 | D77: 19 | E77: 24 | F77: =IF(E77>1, E77/100, E77) -> 0.24 | G77: 4 | H77: 63
A78: C077 | B78: 38503 | C78: 8289 | D78: 24 | E78: 4 | F78: =IF(E78>1, E78/100, E78) -> 0.04 | G78: 4 | H78: 51
A79: C078 | B79: 44146 | C79: 2149 | D79: 26 | E79: 1 | F79: =IF(E79>1, E79/100, E79) -> 1 | G79: 15 | H79: 29
A80: C079 | B80: 12841 | C80: 10690 | D80: 26 | E80: 0.28 | F80: =IF(E80>1, E80/100, E80) -> 0.28 | G80: 5 | H80: 64
A81: C080 | B81: 36268 | C81: 20247 | D81: 13 | E81: 25 | F81: =IF(E81>1, E81/100, E81) -> 0.25 | G81: 18 | H81: 62
A82: C081 | B82: 48747 | C82: 25835 | D82: 27 | E82: 0.01 | F82: =IF(E82>1, E82/100, E82) -> 0.01 | G82: 14 | H82: 49
A83: C082 | B83: 33525 | D83: 28 | E83: 0.26 | F83: =IF(E83>1, E83/100, E83) -> 0.26 | G83: 7 | H83: 55
A84: C083 | B84: 7129 | D84: 14 | E84: 0.11 | F84: =IF(E84>1, E84/100, E84) -> 0.11 | G84: 15 | H84: 59
A85: C084 | B85: 19255 | C85: 25596 | D85: 19 | E85: 0.17 | F85: =IF(E85>1, E85/100, E85) -> 0.17 | G85: 8 | H85: 66
A86: C085 | B86: 33750 | C86: 16340 | D86: 6 | E86: 6 | F86: =IF(E86>1, E86/100, E86) -> 0.06 | G86: 9 | H86: 57
A87: C086 | B87: 8672 | C87: 18165 | D87: 13 | E87: 24 | F87: =IF(E87>1, E87/100, E87) -> 0.24 | G87: 5 | H87: 34
A88: C087 | B88: 5043 | C88: 16827 | D88: 11 | E88: 0.26 | F88: =IF(E88>1, E88/100, E88) -> 0.26 | G88: 1 | H88: 45
A89: C088 | B89: 28951 | C89: 25720 | D89: 13 | E89: 30 | F89: =IF(E89>1, E89/100, E89) -> 0.3 | G89: 7 | H89: 62
A90: C089 | B90: 41194 | C90: 16792 | D90: 5 | E90: 4 | F90: =IF(E90>1, E90/100, E90) -> 0.04 | G90: 14 | H90: 59
A91: C090 | B91: 26014 | C91: 12282 | D91: 5 | E91: 0.08 | F91: =IF(E91>1, E91/100, E91) -> 0.08 | G91: 11 | H91: 12
A92: C091 | B92: 49511 | C92: 3763 | D92: 30 | E92: 2 | F92: =IF(E92>1, E92/100, E92) -> 0.02 | G92: 7 | H92: 64
A93: C092 | B93: 26646 | C93: 6661 | D93: 26 | E93: 0.17 | F93: =IF(E93>1, E93/100, E93) -> 0.17 | G93: 8 | H93: 22
A94: C093 | B94: 39234 | C94: 11465 | D94: 5 | E94: 16 | F94: =IF(E94>1, E94/100, E94) -> 0.16 | G94: 15 | H94: 41
A95: C094 | B95: 7533 | C95: 26705 | D95: 4 | E95: 0.09 | F95: =IF(E95>1, E95/100, E95) -> 0.09 | G95: 11 | H95: 13
A96: C095 | B96: 31527 | C96: 6038 | D96: 18 | E96: 0.1 | F96: =IF(E96>1, E96/100, E96) -> 0.1 | G96: 12 | H96: 1
... A107: C106 | B107: 45929 | C107: 19724 | D107: 18 | E107: 0.08 | F107: =IF(E107>1, E107/100, E107) -> 0.08 | G107: 16 | H107: 65
A108: C107 | B108: 11812 | D108: 24 | E108: 25 | F108: =IF(E108>1, E108/100, E108) -> 0.25 | G108: 8 | H108: 19
A109: C108 | B109: 28729 | C109: 18231 | D109: 24 | E109: 26 | F109: =IF(E109>1, E109/100, E109) -> 0.26 | G109: 3 | H109: 9
A110: C109 | B110: 10721 | C110: 10898 | D110: 23 | E110: 0.27 | F110: =IF(E110>1, E110/100, E110) -> 0.27 | G110: 17 | H110: 37
A111: C110 | B111: 15546 | C111: 29127 | D111: 8 | E111: 20 | F111: =IF(E111>1, E111/100, E111) -> 0.2 | G111: 18 | H111: 51
A112: C111 | B112: 32110 | C112: 3175 | D112: 28 | E112: 28 | F112: =IF(E112>1, E112/100, E112) -> 0.28 | G112: 9 | H112: 54
A113: C112 | B113: 14838 | C113: 10895 | D113: 17 | E113: 30 | F113: =IF(E113>1, E113/100, E113) -> 0.3 | G113: 7 | H113: 66
A114: C113 | B114: 49218 | C114: 20666 | D114: 18 | E114: 11 | F114: =IF(E114>1, E114/100, E114) -> 0.11 | G114: 2 | H114: 16
A115: C114 | B115: 39243 | C115: 23117 | D115: 27 | E115: 5 | F115: =IF(E115>1, E115/100, E115) -> 0.05 | G115: 18 | H115: 51
A116: C115 | B116: 38920 | C116: 15777 | D116: 22 | E116: 0.22 | F116: =IF(E116>1, E116/100, E116) -> 0.22 | G116: 5 | H116: 52
A117: C116 | B117: 24201 | C117: 22690 | D117: 9 | E117: 0.1 | F117: =IF(E117>1, E117/100, E117) -> 0.1 | G117: 2 | H117: 64
A118: C117 | B118: 43400 | D118: 17 | E118: 21 | F118: =IF(E118>1, E118/100, E118) -> 0.21 | G118: 18 | H118: 71
A119: C118 | B119: 1980 | C119: 12365 | D119: 23 | E119: 3 | F119: =IF(E119>1, E119/100, E119) -> 0.03 | G119: 20 | H119: 27
A120: C119 | B120: 5949 | C120: 10192 | D120: 29 | E120: 0.04 | F120: =IF(E120>1, E120/100, E120) -> 0.04 | G120: 13 | H120: 4
A121: C120 | B121: 7435 | C121: 7650 | D121: 16 | E121: 0.2 | F121: =IF(E121>1, E121/100, E121) -> 0.2 | G121: 4 | H121: 19
A122: C121 | B122: 33445 | C122: 29687 | D122: 7 | E122: 0.26 | F122: =IF(E122>1, E122/100, E122) -> 0.26 | G122: 18 | H122: 1
A123: C122 | B123: 38276 | C123: 24917 | D123: 3 | E123: 2 | F123: =IF(E123>1, E123/100, E123) -> 0.02 | G123: 9 | H123: 9
A124: C123 | B124: 16839 | C124: 11200 | D124: 19 | E124: 19 | F124: =IF(E124>1, E124/100, E124) -> 0.19 | G124: 17 | H124: 46
A125: C124 | B125: 47198 | C125: 29362 | D125: 7 | E125: 24 | F125: =IF(E125>1, E125/100, E125) -> 0.24 | G125: 16 | H125: 48
A126: C125 | B126: 32948 | D126: 2 | E126: 0.2 | F126: =IF(E126>1, E126/100, E126) -> 0.2 | G126: 6 | H126: 69
A127: C126 | B127: 48524 | C127: 16959 | D127: 1 | E127: 0.26 | F127: =IF(E127>1, E127/100, E127) -> 0.26 | G127: 20 | H127: 59
A128: C127 | B128: 7497 | C128: 638 | D128: 28 | E128: 21 | F128: =IF(E128>1, E128/100, E128) -> 0.21 | G128: 2 | H128: 52
A129: C128 | B129: 23679 | D129: 8 | E129: 21 | F129: =IF(E129>1, E129/100, E129) -> 0.21 | G129: 0 | H129: 20
A130: C129 | B130: 41075 | C130: 21795 | D130: 9 | E130: 0.17 | F130: =IF(E130>1, E130/100, E130) -> 0.17 | G130: 11 | H130: 65
A131: C130 | B131: 34064 | C131: 28932 | D131: 10 | E131: 29 | F131: =IF(E131>1, E131/100, E131) -> 0.29 | G131: 16 | H131: 40
A132: C131 | B132: 9293 | C132: 4215 | D132: 28 | E132: 0.24 | F132: =IF(E132>1, E132/100, E132) -> 0.24 | G132: 7 | H132: 20
...

Sheet Clean_Data
A1: Customer_ID | B1: Revenue | C1: Cost_to_Serve | D1: Orders | E1: Return_Rate | F1: Support_Tickets | G1: Tenure_Months | H1: Return_Rate_Clean | I1: Cost_Clean | J1: Median_Cost | K1: Revenue_Outlier
A2: =Raw_Data!A2 -> C001 | B2: 2658 | C2: 21973 | D2: 22 | E2: 0.22 | F2: 16 | G2: 23 | H2: =IF(ISNUMBER(SEARCH("%",E2)), VALUE(SUBSTITUTE(E2,"%",""))/100, E2) -> 0.22 | I2: =IF(C2="", $J$2, C2) -> 21973 | J2: =MEDIAN(C:C) -> 16549 | K2: =IF(B2>PERCENTILE($B:$B,0.95),"Yes","No") -> No
A3: =Raw_Data!A3 -> C002 | B3: 5103 | C3: 14484 | D3: 1 | E3: 15% | F3: 18 | G3: 14 | H3: =IF(ISNUMBER(SEARCH("%",E3)), VALUE(SUBSTITUTE(E3,"%",""))/100, E3) -> 0.15 | I3: =IF(C3="", $J$2, C3) -> 14484 | K3: =IF(B3>PERCENTILE($B:$B,0.95),"Yes","No") -> No
A4: =Raw_Data!A4 -> C003 | B4: 25079 | C4: 27280 | D4: 11 | E4: 0.18 | F4: 16 | G4: 56 | H4: =IF(ISNUMBER(SEARCH("%",E4)), VALUE(SUBSTITUTE(E4,"%",""))/100, E4) -> 0.18 | I4: =IF(C4="", $J$2, C4) -> 27280 | K4: =IF(B4>PERCENTILE($B:$B,0.95),"Yes","No") -> No
A5: =Raw_Data!A5 -> C004 | B5: 16960 | C5: 26875 | D5: 12 | E5: 0.21 | F5: 20 | G5: 10 | H5: =IF(ISNUMBER(SEARCH("%",E5)), VALUE(SUBSTITUTE(E5,"%",""))/100, E5) -> 0.21 | I5: =IF(C5="", $J$2, C5) -> 26875 | K5: =IF(B5>PERCENTILE($B:$B,0.95),"Yes","No") -> No
A6: =Raw_Data!A6 -> C005 | B6: 30841 | C6: 7986 | D6: 2 | E6: 0.12 | F6: 5 | G6: 9 | H6: =IF(ISNUMBER(SEARCH("%",E6)), VALUE(SUBSTITUTE(E6,"%",""))/100, E6) -> 0.12 | I6: =IF(C6="", $J$2, C6) -> 7986 | K6: =IF(B6>PERCENTILE($B:$B,0.95),"Yes","No") -> No
A7: =Raw_Data!A7 -> C006 | B7: 25139 | C7: 19876 | D7: 30 | E7: 12% | F7: 15 | G7: 53 | H7: =IF(ISNUMBER(SEARCH("%",E7)), VALUE(SUBSTITUTE(E7,"%",""))/100, E7) -> 0.12 | I7: =IF(C7="", $J$2, C7) -> 19876 | K7: =IF(B7>PERCENTILE($B:$B,0.95),"Yes","No") -> No
A8: =Raw_Data!A8 -> C007 | B8: 11116 | C8: 10808 | D8: 12 | E8: 0.25 | F8: 3 | G8: 11 | H8: =IF(ISNUMBER(SEARCH("%",E8)), VALUE(SUBSTITUTE(E8,"%",""))/100, E8) -> 0.25 | I8: =IF(C8="", $J$2, C8) -> 10808 | K8: =IF(B8>PERCENTILE($B:$B,0.95),"Yes","No") -> No
A9: =Raw_Data!A9 -> C008 | B9: 44869 | C9: 16868 | D9: 22 | E9: 0.24 | F9: 3 | G9: 38 | H9: =IF(ISNUMBER(SEARCH("%",E9)), VALUE(SUBSTITUTE(E9,"%",""))/100, E9) -> 0.24 | I9: =IF(C9="", $J$2, C9) -> 16868 | K9: =IF(B9>PERCENTILE($B:$B,0.95),"Yes","No") -> No
A10: =Raw_Data!A10 -> C009 | B10: 40105 | C10: 2256 | D10: 6 | E10: 0.25 | F10: 20 | G10: 57 | H10: =IF(ISNUMBER(SEARCH("%",E10)), VALUE(SUBSTITUTE(E10,"%",""))/100, E10) -> 0.25 | I10: =IF(C10="", $J$2, C10) -> 2256 | K10: =IF(B10>PERCENTILE($B:$B,0.95),"Yes","No") -> No
A11: =Raw_Data!A11 -> C010 | B11: 48507 | C11: 7943 | D11: 20 | E11: 0.17 | F11: 6 | G11: 39 | H11: =IF(ISNUMBER(SEARCH("%",E11)), VALUE(SUBSTITUTE(E11,"%",""))/100, E11) -> 0.17 | I11: =IF(C11="", $J$2, C11) -> 7943 | K11: =IF(B11>PERCENTILE($B:$B,0.95),"Yes","No") -> Yes
A12: =Raw_Data!A12 -> C011 | B12: 12530 | C12: 23509 | D12: 4 | E12: 0.3 | F12: 16 | G12: 58 | H12: =IF(ISNUMBER(SEARCH("%",E12)), VALUE(SUBSTITUTE(E12,"%",""))/100, E12) -> 0.3 | I12: =IF(C12="", $J$2, C12) -> 23509 | K12: =IF(B12>PERCENTILE($B:$B,0.95),"Yes","No") -> No
A13: =Raw_Data!A13 -> C012 | B13: 13702 | C13: 24076 | D13: 6 | E13: 6% | F13: 11 | G13: 2 | H13: =IF(ISNUMBER(SEARCH("%",E13)), VALUE(SUBSTITUTE(E13,"%",""))/100, E13) -> 0.06 | I13: =IF(C13="", $J$2, C13) -> 24076 | K13: =IF(B13>PERCENTILE($B:$B,0.95),"Yes","No") -> No
A14: =Raw_Data!A14 -> C013 | B14: 49946 | C14: 22297 | D14: 6 | E14: 21% | F14: 2 | G14: 72 | H14: =IF(ISNUMBER(SEARCH("%",E14)), VALUE(SUBSTITUTE(E14,"%",""))/100, E14) -> 0.21 | I14: =IF(C14="", $J$2, C14) -> 22297 | K14: =IF(B14>PERCENTILE($B:$B,0.95),"Yes","No") -> Yes
A15: =Raw_Data!A15 -> C014 | B15: 2841 | C15: 5160 | D15: 20 | E15: 0.14 | F15: 19 | G15: 50 | H15: =IF(ISNUMBER(SEARCH("%",E15)), VALUE(SUBSTITUTE(E15,"%",""))/100, E15) -> 0.14 | I15: =IF(C15="", $J$2, C15) -> 5160 | K15: =IF(B15>PERCENTILE($B:$B,0.95),"Yes","No") -> No
A16: =Raw_Data!A16 -> C015 | B16: 24430 | C16: 19343 | D16: 26 | E16: 19% | F16: 15 | G16: 19 | H16: =IF(ISNUMBER(SEARCH("%",E16)), VALUE(SUBSTITUTE(E16,"%",""))/100, E16) -> 0.19 | I16: =IF(C16="", $J$2, C16) -> 19343 | K16: =IF(B16>PERCENTILE($B:$B,0.95),"Yes","No") -> No
A17: =Raw_Data!A17 -> C016 | B17: 43130 | C17: 21994 | D17: 23 | E17: 0.13 | F17: 14 | G17: 44 | H17: =IF(ISNUMBER(SEARCH("%",E17)), VALUE(SUBSTITUTE(E17,"%",""))/100, E17) -> 0.13 | I17: =IF(C17="", $J$2, C17) -> 21994 | K17: =IF(B17>PERCENTILE($B:$B,0.95),"Yes","No") -> No
A18: =Raw_Data!A18 -> C017 | B18: 41312 | C18: 15974 | D18: 1 | E18: 0.13 | F18: 9 | G18: 30 | H18: =IF(ISNUMBER(SEARCH("%",E18)), VALUE(SUBSTITUTE(E18,"%",""))/100, E18) -> 0.13 | I18: =IF(C18="", $J$2, C18) -> 15974 | K18: =IF(B18>PERCENTILE($B:$B,0.95),"Yes","No") -> No
A19: =Raw_Data!A19 -> C018 | B19: 43466 | C19: 19122 | D19: 5 | E19: 13% | F19: 0 | G19: 11 | H19: =IF(ISNUMBER(SEARCH("%",E19)), VALUE(SUBSTITUTE(E19,"%",""))/100, E19) -> 0.13 | I19: =IF(C19="", $J$2, C19) -> 19122 | K19: =IF(B19>PERCENTILE($B:$B,0.95),"Yes","No") -> No
A20: =Raw_Data!A20 -> C019 | B20: 6420 | C20: 14730 | D20: 30 | E20: 0.02 | F20: 8 | G20: 57 | H20: =IF(ISNUMBER(SEARCH("%",E20)), VALUE(SUBSTITUTE(E20,"%",""))/100, E20) -> 0.02 | I20: =IF(C20="", $J$2, C20) -> 14730 | K20: =IF(B20>PERCENTILE($B:$B,0.95),"Yes","No") -> No
A21: =Raw_Data!A21 -> C020 | B21: 38243 | C21: 7779 | D21: 9 | E21: 6% | F21: 14 | G21: 1 | H21: =IF(ISNUMBER(SEARCH("%",E21)), VALUE(SUBSTITUTE(E21,"%",""))/100, E21) -> 0.06 | I21: =IF(C21="", $J$2, C21) -> 7779 | K21: =IF(B21>PERCENTILE($B:$B,0.95),"Yes","No") -> No
A22: =Raw_Data!A22 -> C021 | B22: 47981 | C22: 12177 | D22: 2 | E22: 0.25 | F22: 17 | G22: 69 | H22: =IF(ISNUMBER(SEARCH("%",E22)), VALUE(SUBSTITUTE(E22,"%",""))/100, E22) -> 0.25 | I22: =IF(C22="", $J$2, C22) -> 12177 | K22: =IF(B22>PERCENTILE($B:$B,0.95),"Yes","No") -> No
A23: =Raw_Data!A23 -> C022 | B23: 48072 | C23: 27827 | D23: 28 | E23: 30% | F23: 1 | G23: 6 | H23: =IF(ISNUMBER(SEARCH("%",E23)), VALUE(SUBSTITUTE(E23,"%",""))/100, E23) -> 0.3 | I23: =IF(C23="", $J$2, C23) -> 27827 | K23: =IF(B23>PERCENTILE($B:$B,0.95),"Yes","No") -> No
A24: =Raw_Data!A24 -> C023 | B24: 2729 | C24: 28066 | D24: 12 | E24: 0.18 | F24: 15 | G24: 71 | H24: =IF(ISNUMBER(SEARCH("%",E24)), VALUE(SUBSTITUTE(E24,"%",""))/100, E24) -> 0.18 | I24: =IF(C24="", $J$2, C24) -> 28066 | K24: =IF(B24>PERCENTILE($B:$B,0.95),"Yes","No") -> No
A25: =Raw_Data!A25 -> C024 | B25: 48456 | C25: 29990 | D25: 24 | E25: 0.19 | F25: 0 | G25: 27 | H25: =IF(ISNUMBER(SEARCH("%",E25)), VALUE(SUBSTITUTE(E25,"%",""))/100, E25) -> 0.19 | I25: =IF(C25="", $J$2, C25) -> 29990 | K25: =IF(B25>PERCENTILE($B:$B,0.95),"Yes","No") -> Yes
A26: =Raw_Data!A26 -> C025 | B26: 42662 | C26: 22929 | D26: 21 | E26: 0.19 | F26: 3 | G26: 14 | H26: =IF(ISNUMBER(SEARCH("%",E26)), VALUE(SUBSTITUTE(E26,"%",""))/100, E26) -> 0.19 | I26: =IF(C26="", $J$2, C26) -> 22929 | K26: =IF(B26>PERCENTILE($B:$B,0.95),"Yes","No") -> No
A27: =Raw_Data!A27 -> C026 | B27: 35379 | C27: 11518 | D27: 7 | E27: 7% | F27: 19 | G27: 38 | H27: =IF(ISNUMBER(SEARCH("%",E27)), VALUE(SUBSTITUTE(E27,"%",""))/100, E27) -> 0.07 | I27: =IF(C27="", $J$2, C27) -> 11518 | K27: =IF(B27>PERCENTILE($B:$B,0.95),"Yes","No") -> No
A28: =Raw_Data!A28 -> C027 | B28: 38190 | C28: 22035 | D28: 11 | E28: 0.07 | F28: 3 | G28: 10 | H28: =IF(ISNUMBER(SEARCH("%",E28)), VALUE(SUBSTITUTE(E28,"%",""))/100, E28) -> 0.07 | I28: =IF(C28="", $J$2, C28) -> 22035 | K28: =IF(B28>PERCENTILE($B:$B,0.95),"Yes","No") -> No
A29: =Raw_Data!A29 -> C028 | B29: 31980 | C29: 2145 | D29: 24 | E29: 0.17 | F29: 1 | G29: 48 | H29: =IF(ISNUMBER(SEARCH("%",E29)), VALUE(SUBSTITUTE(E29,"%",""))/100, E29) -> 0.17 | I29: =IF(C29="", $J$2, C29) -> 2145 | K29: =IF(B29>PERCENTILE($B:$B,0.95),"Yes","No") -> No
A30: =Raw_Data!A30 -> C029 | B30: 33508 | C30: 7252 | D30: 27 | E30: 3% | F30: 14 | G30: 16 | H30: =IF(ISNUMBER(SEARCH("%",E30)), VALUE(SUBSTITUTE(E30,"%",""))/100, E30) -> 0.03 | I30: =IF(C30="", $J$2, C30) -> 7252 | K30: =IF(B30>PERCENTILE($B:$B,0.95),"Yes","No") -> No
A31: =Raw_Data!A31 -> C030 | B31: 31918 | D31: 9 | E31: 24% | F31: 20 | G31: 55 | H31: =IF(ISNUMBER(SEARCH("%",E31)), VALUE(SUBSTITUTE(E31,"%",""))/100, E31) -> 0.24 | I31: =IF(C31="", $J$2, C31) -> 16549 | K31: =IF(B31>PERCENTILE($B:$B,0.95),"Yes","No") -> No
A32: =Raw_Data!A32 -> C031 | B32: 21796 | C32: 24046 | D32: 20 | E32: 15% | F32: 18 | G32: 54 | H32: =IF(ISNUMBER(SEARCH("%",E32)), VALUE(SUBSTITUTE(E32,"%",""))/100, E32) -> 0.15 | I32: =IF(C32="", $J$2, C32) -> 24046 | K32: =IF(B32>PERCENTILE($B:$B,0.95),"Yes","No") -> No
A33: =Raw_Data!A33 -> C032 | B33: 49521 | C33: 19342 | D33: 5 | E33: 0.21 | F33: 8 | G33: 60 | H33: =IF(ISNUMBER(SEARCH("%",E33)), VALUE(SUBSTITUTE(E33,"%",""))/100, E33) -> 0.21 | I33: =IF(C33="", $J$2, C33) -> 19342 | K33: =IF(B33>PERCENTILE($B:$B,0.95),"Yes","No") -> Yes
A34: =Raw_Data!A34 -> C033 | B34: 24992 | C34: 6860 | D34: 25 | E34: 15% | F34: 15 | G34: 65 | H34: =IF(ISNUMBER(SEARCH("%",E34)), VALUE(SUBSTITUTE(E34,"%",""))/100, E34) -> 0.15 | I34: =IF(C34="", $J$2, C34) -> 6860 | K34: =IF(B34>PERCENTILE($B:$B,0.95),"Yes","No") -> No
A35: =Raw_Data!A35 -> C034 | B35: 14168 | C35: 2237 | D35: 6 | E35: 0.25 | F35: 3 | G35: 60 | H35: =IF(ISNUMBER(SEARCH("%",E35)), VALUE(SUBSTITUTE(E35,"%",""))/100, E35) -> 0.25 | I35: =IF(C35="", $J$2, C35) -> 2237 | K35: =IF(B35>PERCENTILE($B:$B,0.95),"Yes","No") -> No
A36: =Raw_Data!A36 -> C035 | B36: 13475 | C36: 3293 | D36: 9 | E36: 0.29 | F36: 17 | G36: 8 | H36: =IF(ISNUMBER(SEARCH("%",E36)), VALUE(SUBSTITUTE(E36,"%",""))/100, E36) -> 0.29 | I36: =IF(C36="", $J$2, C36) -> 3293 | K36: =IF(B36>PERCENTILE($B:$B,0.95),"Yes","No") -> No
A37: =Raw_Data!A37 -> C036 | B37: 29892 | C37: 28329 | D37: 14 | E37: 8% | F37: 2 | G37: 67 | H37: =IF(ISNUMBER(SEARCH("%",E37)), VALUE(SUBSTITUTE(E37,"%",""))/100, E37) -> 0.08 | I37: =IF(C37="", $J$2, C37) -> 28329 | K37: =IF(B37>PERCENTILE($B:$B,0.95),"Yes","No") -> No
A38: =Raw_Data!A38 -> C037 | B38: 10507 | C38: 28524 | D38: 20 | E38: 23% | F38: 3 | G38: 30 | H38: =IF(ISNUMBER(SEARCH("%",E38)), VALUE(SUBSTITUTE(E38,"%",""))/100, E38) -> 0.23 | I38: =IF(C38="", $J$2, C38) -> 28524 | K38: =IF(B38>PERCENTILE($B:$B,0.95),"Yes","No") -> No
A39: =Raw_Data!A39 -> C038 | B39: 44476 | C39: 8811 | D39: 8 | E39: 0.26 | F39: 10 | G39: 62 | H39: =IF(ISNUMBER(SEARCH("%",E39)), VALUE(SUBSTITUTE(E39,"%",""))/100, E39) -> 0.26 | I39: =IF(C39="", $J$2, C39) -> 8811 | K39: =IF(B39>PERCENTILE($B:$B,0.95),"Yes","No") -> No
A40: =Raw_Data!A40 -> C039 | B40: 17860 | C40: 23935 | D40: 26 | E40: 0.05 | F40: 16 | G40: 29 | H40: =IF(ISNUMBER(SEARCH("%",E40)), VALUE(SUBSTITUTE(E40,"%",""))/100, E40) -> 0.05 | I40: =IF(C40="", $J$2, C40) -> 23935 | K40: =IF(B40>PERCENTILE($B:$B,0.95),"Yes","No") -> No
A41: =Raw_Data!A41 -> C040 | B41: 16645 | C41: 29691 | D41: 8 | E41: 30% | F41: 13 | G41: 67 | H41: =IF(ISNUMBER(SEARCH("%",E41)), VALUE(SUBSTITUTE(E41,"%",""))/100, E41) -> 0.3 | I41: =IF(C41="", $J$2, C41) -> 29691 | K41: =IF(B41>PERCENTILE($B:$B,0.95),"Yes","No") -> No
A42: =Raw_Data!A42 -> C041 | B42: 8465 | C42: 27589 | D42: 6 | E42: 0.06 | F42: 1 | G42: 34 | H42: =IF(ISNUMBER(SEARCH("%",E42)), VALUE(SUBSTITUTE(E42,"%",""))/100, E42) -> 0.06 | I42: =IF(C42="", $J$2, C42) -> 27589 | K42: =IF(B42>PERCENTILE($B:$B,0.95),"Yes","No") -> No
A43: =Raw_Data!A43 -> C042 | B43: 43908 | C43: 24510 | D43: 25 | E43: 17% | F43: 19 | G43: 72 | H43: =IF(ISNUMBER(SEARCH("%",E43)), VALUE(SUBSTITUTE(E43,"%",""))/100, E43) -> 0.17 | I43: =IF(C43="", $J$2, C43) -> 24510 | K43: =IF(B43>PERCENTILE($B:$B,0.95),"Yes","No") -> No
A44: =Raw_Data!A44 -> C043 | B44: 20014 | C44: 5860 | D44: 15 | E44: 0.17 | F44: 7 | G44: 4 | H44: =IF(ISNUMBER(SEARCH("%",E44)), VALUE(SUBSTITUTE(E44,"%",""))/100, E44) -> 0.17 | I44: =IF(C44="", $J$2, C44) -> 5860 | K44: =IF(B44>PERCENTILE($B:$B,0.95),"Yes","No") -> No
A45: =Raw_Data!A45 -> C044 | B45: 9133 | C45: 29513 | D45: 21 | E45: 0.3 | F45: 18 | G45: 61 | H45: =IF(ISNUMBER(SEARCH("%",E45)), VALUE(SUBSTITUTE(E45,"%",""))/100, E45) -> 0.3 | I45: =IF(C45="", $J$2, C45) -> 29513 | K45: =IF(B45>PERCENTILE($B:$B,0.95),"Yes","No") -> No
A46: =Raw_Data!A46 -> C045 | B46: 21037 | C46: 15022 | D46: 12 | E46: 0.01 | F46: 6 | G46: 44 | H46: =IF(ISNUMBER(SEARCH("%",E46)), VALUE(SUBSTITUTE(E46,"%",""))/100, E46) -> 0.01 | I46: =IF(C46="", $J$2, C46) -> 15022 | K46: =IF(B46>PERCENTILE($B:$B,0.95),"Yes","No") -> No
A47: =Raw_Data!A47 -> C046 | B47: 37702 | C47: 5541 | D47: 17 | E47: 8% | F47: 4 | G47: 52 | H47: =IF(ISNUMBER(SEARCH("%",E47)), VALUE(SUBSTITUTE(E47,"%",""))/100, E47) -> 0.08 | I47: =IF(C47="", $J$2, C47) -> 5541 | K47: =IF(B47>PERCENTILE($B:$B,0.95),"Yes","No") -> No
A48: =Raw_Data!A48 -> C047 | B48: 15213 | D48: 11 | E48: 0.05 | F48: 0 | G48: 69 | H48: =IF(ISNUMBER(SEARCH("%",E48)), VALUE(SUBSTITUTE(E48,"%",""))/100, E48) -> 0.05 | I48: =IF(C48="", $J$2, C48) -> 16549 | K48: =IF(B48>PERCENTILE($B:$B,0.95),"Yes","No") -> No
A49: =Raw_Data!A49 -> C048 | B49: 38465 | D49: 2 | E49: 25% | F49: 0 | G49: 12 | H49: =IF(ISNUMBER(SEARCH("%",E49)), VALUE(SUBSTITUTE(E49,"%",""))/100, E49) -> 0.25 | I49: =IF(C49="", $J$2, C49) -> 16549 | K49: =IF(B49>PERCENTILE($B:$B,0.95),"Yes","No") -> No
A50: =Raw_Data!A50 -> C049 | B50: 40964 | C50: 7316 | D50: 27 | E50: 0.3 | F50: 15 | G50: 45 | H50: =IF(ISNUMBER(SEARCH("%",E50)), VALUE(SUBSTITUTE(E50,"%",""))/100, E50) -> 0.3 | I50: =IF(C50="", $J$2, C50) -> 7316 | K50: =IF(B50>PERCENTILE($B:$B,0.95),"Yes","No") -> No
A51: =Raw_Data!A51 -> C050 | B51: 3354 | C51: 26453 | D51: 5 | E51: 10% | F51: 2 | G51: 55 | H51: =IF(ISNUMBER(SEARCH("%",E51)), VALUE(SUBSTITUTE(E51,"%",""))/100, E51) -> 0.1 | I51: =IF(C51="", $J$2, C51) -> 26453 | K51: =IF(B51>PERCENTILE($B:$B,0.95),"Yes","No") -> No
A52: =Raw_Data!A52 -> C051 | B52: 39754 | C52: 17071 | D52: 7 | E52: 0.19 | F52: 10 | G52: 65 | H52: =IF(ISNUMBER(SEARCH("%",E52)), VALUE(SUBSTITUTE(E52,"%",""))/100, E52) -> 0.19 | I52: =IF(C52="", $J$2, C52) -> 17071 | K52: =IF(B52>PERCENTILE($B:$B,0.95),"Yes","No") -> No
A53: =Raw_Data!A53 -> C052 | B53: 9655 | C53: 9733 | D53: 24 | E53: 0.13 | F53: 2 | G53: 46 | H53: =IF(ISNUMBER(SEARCH("%",E53)), VALUE(SUBSTITUTE(E53,"%",""))/100, E53) -> 0.13 | I53: =IF(C53="", $J$2, C53) -> 9733 | K53: =IF(B53>PERCENTILE($B:$B,0.95),"Yes","No") -> No
A54: =Raw_Data!A54 -> C053 | B54: 14600 | C54: 13535 | D54: 17 | E54: 13% | F54: 16 | G54: 14 | H54: =IF(ISNUMBER(SEARCH("%",E54)), VALUE(SUBSTITUTE(E54,"%",""))/100, E54) -> 0.13 | I54: =IF(C54="", $J$2, C54) -> 13535 | K54: =IF(B54>PERCENTILE($B:$B,0.95),"Yes","No") -> No
A55: =Raw_Data!A55 -> C054 | B55: 43298 | C55: 7241 | D55: 22 | E55: 3% | F55: 18 | G55: 30 | H55: =IF(ISNUMBER(SEARCH("%",E55)), VALUE(SUBSTITUTE(E55,"%",""))/100, E55) -> 0.03 | I55: =IF(C55="", $J$2, C55) -> 7241 | K55: =IF(B55>PERCENTILE($B:$B,0.95),"Yes","No") -> No
A56: =Raw_Data!A56 -> C055 | B56: 20624 | C56: 26135 | D56: 26 | E56: 0.18 | F56: 20 | G56: 42 | H56: =IF(ISNUMBER(SEARCH("%",E56)), VALUE(SUBSTITUTE(E56,"%",""))/100, E56) -> 0.18 | I56: =IF(C56="", $J$2, C56) -> 26135 | K56: =IF(B56>PERCENTILE($B:$B,0.95),"Yes","No") -> No
A57: =Raw_Data!A57 -> C056 | B57: 24598 | C57: 8860 | D57: 22 | E57: 19% | F57: 20 | G57: 35 | H57: =IF(ISNUMBER(SEARCH("%",E57)), VALUE(SUBSTITUTE(E57,"%",""))/100, E57) -> 0.19 | I57: =IF(C57="", $J$2, C57) -> 8860 | K57: =IF(B57>PERCENTILE($B:$B,0.95),"Yes","No") -> No
A58: =Raw_Data!A58 -> C057 | B58: 30928 | C58: 11129 | D58: 15 | E58: 30% | F58: 19 | G58: 56 | H58: =IF(ISNUMBER(SEARCH("%",E58)), VALUE(SUBSTITUTE(E58,"%",""))/100, E58) -> 0.3 | I58: =IF(C58="", $J$2, C58) -> 11129 | K58: =IF(B58>PERCENTILE($B:$B,0.95),"Yes","No") -> No
A59: =Raw_Data!A59 -> C058 | B59: 5161 | D59: 25 | E59: 28% | F59: 9 | G59: 48 | H59: =IF(ISNUMBER(SEARCH("%",E59)), VALUE(SUBSTITUTE(E59,"%",""))/100, E59) -> 0.28 | I59: =IF(C59="", $J$2, C59) -> 16549 | K59: =IF(B59>PERCENTILE($B:$B,0.95),"Yes","No") -> No
A60: =Raw_Data!A60 -> C059 | B60: 44453 | C60: 11062 | D60: 15 | E60: 0.02 | F60: 8 | G60: 22 | H60: =IF(ISNUMBER(SEARCH("%",E60)), VALUE(SUBSTITUTE(E60,"%",""))/100, E60) -> 0.02 | I60: =IF(C60="", $J$2, C60) -> 11062 | K60: =IF(B60>PERCENTILE($B:$B,0.95),"Yes","No") -> No
A61: =Raw_Data!A61 -> C060 | B61: 30775 | C61: 17693 | D61: 9 | E61: 0.17 | F61: 8 | G61: 18 | H61: =IF(ISNUMBER(SEARCH("%",E61)), VALUE(SUBSTITUTE(E61,"%",""))/100, E61) -> 0.17 | I61: =IF(C61="", $J$2, C61) -> 17693 | K61: =IF(B61>PERCENTILE($B:$B,0.95),"Yes","No") -> No
A62: =Raw_Data!A62 -> C061 | B62: 19789 | C62: 6752 | D62: 17 | E62: 10% | F62: 16 | G62: 4 | H62: =IF(ISNUMBER(SEARCH("%",E62)), VALUE(SUBSTITUTE(E62,"%",""))/100, E62) -> 0.1 | I62: =IF(C62="", $J$2, C62) -> 6752 | K62: =IF(B62>PERCENTILE($B:$B,0.95),"Yes","No") -> No
A63: =Raw_Data!A63 -> C062 | B63: 43255 | C63: 14529 | D63: 14 | E63: 20% | F63: 19 | G63: 12 | H63: =IF(ISNUMBER(SEARCH("%",E63)), VALUE(SUBSTITUTE(E63,"%",""))/100, E63) -> 0.2 | I63: =IF(C63="", $J$2, C63) -> 14529 | K63: =IF(B63>PERCENTILE($B:$B,0.95),"Yes","No") -> No
A64: =Raw_Data!A64 -> C063 | B64: 4506 | C64: 21797 | D64: 28 | E64: 0.17 | F64: 19 | G64: 35 | H64: =IF(ISNUMBER(SEARCH("%",E64)), VALUE(SUBSTITUTE(E64,"%",""))/100, E64) -> 0.17 | I64: =IF(C64="", $J$2, C64) -> 21797 | K64: =IF(B64>PERCENTILE($B:$B,0.95),"Yes","No") -> No
A65: =Raw_Data!A65 -> C064 | B65: 22342 | C65: 21828 | D65: 10 | E65: 0.1 | F65: 5 | G65: 4 | H65: =IF(ISNUMBER(SEARCH("%",E65)), VALUE(SUBSTITUTE(E65,"%",""))/100, E65) -> 0.1 | I65: =IF(C65="", $J$2, C65) -> 21828 | K65: =IF(B65>PERCENTILE($B:$B,0.95),"Yes","No") -> No
A66: =Raw_Data!A66 -> C065 | B66: 37720 | C66: 19960 | D66: 4 | E66: 22% | F66: 19 | G66: 41 | H66: =IF(ISNUMBER(SEARCH("%",E66)), VALUE(SUBSTITUTE(E66,"%",""))/100, E66) -> 0.22 | I66: =IF(C66="", $J$2, C66) -> 19960 | K66: =IF(B66>PERCENTILE($B:$B,0.95),"Yes","No") -> No
A67: =Raw_Data!A67 -> C066 | B67: 30383 | C67: 15094 | D67: 17 | E67: 0.23 | F67: 14 | G67: 28 | H67: =IF(ISNUMBER(SEARCH("%",E67)), VALUE(SUBSTITUTE(E67,"%",""))/100, E67) -> 0.23 | I67: =IF(C67="", $J$2, C67) -> 15094 | K67: =IF(B67>PERCENTILE($B:$B,0.95),"Yes","No") -> No
A68: =Raw_Data!A68 -> C067 | B68: 9858 | C68: 3881 | D68: 1 | E68: 9% | F68: 19 | G68: 63 | H68: =IF(ISNUMBER(SEARCH("%",E68)), VALUE(SUBSTITUTE(E68,"%",""))/100, E68) -> 0.09 | I68: =IF(C68="", $J$2, C68) -> 3881 | K68: =IF(B68>PERCENTILE($B:$B,0.95),"Yes","No") -> No
A69: =Raw_Data!A69 -> C068 | B69: 48100 | C69: 27774 | D69: 17 | E69: 0.02 | F69: 7 | G69: 44 | H69: =IF(ISNUMBER(SEARCH("%",E69)), VALUE(SUBSTITUTE(E69,"%",""))/100, E69) -> 0.02 | I69: =IF(C69="", $J$2, C69) -> 27774 | K69: =IF(B69>PERCENTILE($B:$B,0.95),"Yes","No") -> No
A70: =Raw_Data!A70 -> C069 | B70: 21859 | C70: 19192 | D70: 1 | E70: 0.19 | F70: 13 | G70: 6 | H70: =IF(ISNUMBER(SEARCH("%",E70)), VALUE(SUBSTITUTE(E70,"%",""))/100, E70) -> 0.19 | I70: =IF(C70="", $J$2, C70) -> 19192 | K70: =IF(B70>PERCENTILE($B:$B,0.95),"Yes","No") -> No
A71: =Raw_Data!A71 -> C070 | B71: 45655 | C71: 25708 | D71: 26 | E71: 0.17 | F71: 13 | G71: 21 | H71: =IF(ISNUMBER(SEARCH("%",E71)), VALUE(SUBSTITUTE(E71,"%",""))/100, E71) -> 0.17 | I71: =IF(C71="", $J$2, C71) -> 25708 | K71: =IF(B71>PERCENTILE($B:$B,0.95),"Yes","No") -> No
A72: =Raw_Data!A72 -> C071 | B72: 27500 | C72: 14556 | D72: 7 | E72: 0.07 | F72: 20 | G72: 35 | H72: =IF(ISNUMBER(SEARCH("%",E72)), VALUE(SUBSTITUTE(E72,"%",""))/100, E72) -> 0.07 | I72: =IF(C72="", $J$2, C72) -> 14556 | K72: =IF(B72>PERCENTILE($B:$B,0.95),"Yes","No") -> No
A73: =Raw_Data!A73 -> C072 | B73: 14245 | C73: 5635 | D73: 22 | E73: 0.25 | F73: 19 | G73: 19 | H73: =IF(ISNUMBER(SEARCH("%",E73)), VALUE(SUBSTITUTE(E73,"%",""))/100, E73) -> 0.25 | I73: =IF(C73="", $J$2, C73) -> 5635 | K73: =IF(B73>PERCENTILE($B:$B,0.95),"Yes","No") -> No
A74: =Raw_Data!A74 -> C073 | B74: 25665 | C74: 9918 | D74: 30 | E74: 4% | F74: 11 | G74: 37 | H74: =IF(ISNUMBER(SEARCH("%",E74)), VALUE(SUBSTITUTE(E74,"%",""))/100, E74) -> 0.04 | I74: =IF(C74="", $J$2, C74) -> 9918 | K74: =IF(B74>PERCENTILE($B:$B,0.95),"Yes","No") -> No
A75: =Raw_Data!A75 -> C074 | B75: 14069 | C75: 13970 | D75: 26 | E75: 20% | F75: 11 | G75: 20 | H75: =IF(ISNUMBER(SEARCH("%",E75)), VALUE(SUBSTITUTE(E75,"%",""))/100, E75) -> 0.2 | I75: =IF(C75="", $J$2, C75) -> 13970 | K75: =IF(B75>PERCENTILE($B:$B,0.95),"Yes","No") -> No
A76: =Raw_Data!A76 -> C075 | B76: 49591 | D76: 26 | E76: 0.15 | F76: 0 | G76: 51 | H76: =IF(ISNUMBER(SEARCH("%",E76)), VALUE(SUBSTITUTE(E76,"%",""))/100, E76) -> 0.15 | I76: =IF(C76="", $J$2, C76) -> 16549 | K76: =IF(B76>PERCENTILE($B:$B,0.95),"Yes","No") -> Yes
A77: =Raw_Data!A77 -> C076 | B77: 27050 | C77: 17324 | D77: 19 | E77: 24% | F77: 4 | G77: 63 | H77: =IF(ISNUMBER(SEARCH("%",E77)), VALUE(SUBSTITUTE(E77,"%",""))/100, E77) -> 0.24 | I77: =IF(C77="", $J$2, C77) -> 17324 | K77: =IF(B77>PERCENTILE($B:$B,0.95),"Yes","No") -> No
A78: =Raw_Data!A78 -> C077 | B78: 38503 | C78: 8289 | D78: 24 | E78: 4% | F78: 4 | G78: 51 | H78: =IF(ISNUMBER(SEARCH("%",E78)), VALUE(SUBSTITUTE(E78,"%",""))/100, E78) -> 0.04 | I78: =IF(C78="", $J$2, C78) -> 8289 | K78: =IF(B78>PERCENTILE($B:$B,0.95),"Yes","No") -> No
A79: =Raw_Data!A79 -> C078 | B79: 44146 | C79: 2149 | D79: 26 | E79: 1% | F79: 15 | G79: 29 | H79: =IF(ISNUMBER(SEARCH("%",E79)), VALUE(SUBSTITUTE(E79,"%",""))/100, E79) -> 0.01 | I79: =IF(C79="", $J$2, C79) -> 2149 | K79: =IF(B79>PERCENTILE($B:$B,0.95),"Yes","No") -> No
A80: =Raw_Data!A80 -> C079 | B80: 12841 | C80: 10690 | D80: 26 | E80: 0.28 | F80: 5 | G80: 64 | H80: =IF(ISNUMBER(SEARCH("%",E80)), VALUE(SUBSTITUTE(E80,"%",""))/100, E80) -> 0.28 | I80: =IF(C80="", $J$2, C80) -> 10690 | K80: =IF(B80>PERCENTILE($B:$B,0.95),"Yes","No") -> No
A81: =Raw_Data!A81 -> C080 | B81: 36268 | C81: 20247 | D81: 13 | E81: 25% | F81: 18 | G81: 62 | H81: =IF(ISNUMBER(SEARCH("%",E81)), VALUE(SUBSTITUTE(E81,"%",""))/100, E81) -> 0.25 | I81: =IF(C81="", $J$2, C81) -> 20247 | K81: =IF(B81>PERCENTILE($B:$B,0.95),"Yes","No") -> No
A82: =Raw_Data!A82 -> C081 | B82: 48747 | C82: 25835 | D82: 27 | E82: 0.01 | F82: 14 | G82: 49 | H82: =IF(ISNUMBER(SEARCH("%",E82)), VALUE(SUBSTITUTE(E82,"%",""))/100, E82) -> 0.01 | I82: =IF(C82="", $J$2, C82) -> 25835 | K82: =IF(B82>PERCENTILE($B:$B,0.95),"Yes","No") -> Yes
A83: =Raw_Data!A83 -> C082 | B83: 33525 | D83: 28 | E83: 0.26 | F83: 7 | G83: 55 | H83: =IF(ISNUMBER(SEARCH("%",E83)), VALUE(SUBSTITUTE(E83,"%",""))/100, E83) -> 0.26 | I83: =IF(C83="", $J$2, C83) -> 16549 | K83: =IF(B83>PERCENTILE($B:$B,0.95),"Yes","No") -> No
A84: =Raw_Data!A84 -> C083 | B84: 7129 | D84: 14 | E84: 0.11 | F84: 15 | G84: 59 | H84: =IF(ISNUMBER(SEARCH("%",E84)), VALUE(SUBSTITUTE(E84,"%",""))/100, E84) -> 0.11 | I84: =IF(C84="", $J$2, C84) -> 16549 | K84: =IF(B84>PERCENTILE($B:$B,0.95),"Yes","No") -> No
A85: =Raw_Data!A85 -> C084 | B85: 19255 | C85: 25596 | D85: 19 | E85: 0.17 | F85: 8 | G85: 66 | H85: =IF(ISNUMBER(SEARCH("%",E85)), VALUE(SUBSTITUTE(E85,"%",""))/100, E85) -> 0.17 | I85: =IF(C85="", $J$2, C85) -> 25596 | K85: =IF(B85>PERCENTILE($B:$B,0.95),"Yes","No") -> No
A86: =Raw_Data!A86 -> C085 | B86: 33750 | C86: 16340 | D86: 6 | E86: 6% | F86: 9 | G86: 57 | H86: =IF(ISNUMBER(SEARCH("%",E86)), VALUE(SUBSTITUTE(E86,"%",""))/100, E86) -> 0.06 | I86: =IF(C86="", $J$2, C86) -> 16340 | K86: =IF(B86>PERCENTILE($B:$B,0.95),"Yes","No") -> No
A87: =Raw_Data!A87 -> C086 | B87: 8672 | C87: 18165 | D87: 13 | E87: 24% | F87: 5 | G87: 34 | H87: =IF(ISNUMBER(SEARCH("%",E87)), VALUE(SUBSTITUTE(E87,"%",""))/100, E87) -> 0.24 | I87: =IF(C87="", $J$2, C87) -> 18165 | K87: =IF(B87>PERCENTILE($B:$B,0.95),"Yes","No") -> No
A88: =Raw_Data!A88 -> C087 | B88: 5043 | C88: 16827 | D88: 11 | E88: 0.26 | F88: 1 | G88: 45 | H88: =IF(ISNUMBER(SEARCH("%",E88)), VALUE(SUBSTITUTE(E88,"%",""))/100, E88) -> 0.26 | I88: =IF(C88="", $J$2, C88) -> 16827 | K88: =IF(B88>PERCENTILE($B:$B,0.95),"Yes","No") -> No
A89: =Raw_Data!A89 -> C088 | B89: 28951 | C89: 25720 | D89: 13 | E89: 30% | F89: 7 | G89: 62 | H89: =IF(ISNUMBER(SEARCH("%",E89)), VALUE(SUBSTITUTE(E89,"%",""))/100, E89) -> 0.3 | I89: =IF(C89="", $J$2, C89) -> 25720 | K89: =IF(B89>PERCENTILE($B:$B,0.95),"Yes","No") -> No
A90: =Raw_Data!A90 -> C089 | B90: 41194 | C90: 16792 | D90: 5 | E90: 4% | F90: 14 | G90: 59 | H90: =IF(ISNUMBER(SEARCH("%",E90)), VALUE(SUBSTITUTE(E90,"%",""))/100, E90) -> 0.04 | I90: =IF(C90="", $J$2, C90) -> 16792 | K90: =IF(B90>PERCENTILE($B:$B,0.95),"Yes","No") -> No
A91: =Raw_Data!A91 -> C090 | B91: 26014 | C91: 12282 | D91: 5 | E91: 0.08 | F91: 11 | G91: 12 | H91: =IF(ISNUMBER(SEARCH("%",E91)), VALUE(SUBSTITUTE(E91,"%",""))/100, E91) -> 0.08 | I91: =IF(C91="", $J$2, C91) -> 12282 | K91: =IF(B91>PERCENTILE($B:$B,0.95),"Yes","No") -> No
A92: =Raw_Data!A92 -> C091 | B92: 49511 | C92: 3763 | D92: 30 | E92: 2% | F92: 7 | G92: 64 | H92: =IF(ISNUMBER(SEARCH("%",E92)), VALUE(SUBSTITUTE(E92,"%",""))/100, E92) -> 0.02 | I92: =IF(C92="", $J$2, C92) -> 3763 | K92: =IF(B92>PERCENTILE($B:$B,0.95),"Yes","No") -> Yes
A93: =Raw_Data!A93 -> C092 | B93: 26646 | C93: 6661 | D93: 26 | E93: 0.17 | F93: 8 | G93: 22 | H93: =IF(ISNUMBER(SEARCH("%",E93)), VALUE(SUBSTITUTE(E93,"%",""))/100, E93) -> 0.17 | I93: =IF(C93="", $J$2, C93) -> 6661 | K93: =IF(B93>PERCENTILE($B:$B,0.95),"Yes","No") -> No
A94: =Raw_Data!A94 -> C093 | B94: 39234 | C94: 11465 | D94: 5 | E94: 16% | F94: 15 | G94: 41 | H94: =IF(ISNUMBER(SEARCH("%",E94)), VALUE(SUBSTITUTE(E94,"%",""))/100, E94) -> 0.16 | I94: =IF(C94="", $J$2, C94) -> 11465 | K94: =IF(B94>PERCENTILE($B:$B,0.95),"Yes","No") -> No
A95: =Raw_Data!A95 -> C094 | B95: 7533 | C95: 26705 | D95: 4 | E95: 0.09 | F95: 11 | G95: 13 | H95: =IF(ISNUMBER(SEARCH("%",E95)), VALUE(SUBSTITUTE(E95,"%",""))/100, E95) -> 0.09 | I95: =IF(C95="", $J$2, C95) -> 26705 | K95: =IF(B95>PERCENTILE($B:$B,0.95),"Yes","No") -> No
A96: =Raw_Data!A96 -> C095 | B96: 31527 | C96: 6038 | D96: 18 | E96: 0.1 | F96: 12 | G96: 1 | H96: =IF(ISNUMBER(SEARCH("%",E96)), VALUE(SUBSTITUTE(E96,"%",""))/100, E96) -> 0.1 | I96: =IF(C96="", $J$2, C96) -> 6038 | K96: =IF(B96>PERCENTILE($B:$B,0.95),"Yes","No") -> No
A97: =Raw_Data!A97 -> C096 | B97: 31344 | C97: 18965 | D97: 30 | E97: 14% | F97: 6 | G97: 45 | H97: =IF(ISNUMBER(SEARCH("%",E97)), VALUE(SUBSTITUTE(E97,"%",""))/100, E97) -> 0.14 | I97: =IF(C97="", $J$2, C97) -> 18965 | K97: =IF(B97>PERCENTILE($B:$B,0.95),"Yes","No") -> No
A98: =Raw_Data!A98 -> C097 | B98: 24525 | C98: 9483 | D98: 23 | E98: 27% | F98: 11 | G98: 53 | H98: =IF(ISNUMBER(SEARCH("%",E98)), VALUE(SUBSTITUTE(E98,"%",""))/100, E98) -> 0.27 | I98: =IF(C98="", $J$2, C98) -> 9483 | K98: =IF(B98>PERCENTILE($B:$B,0.95),"Yes","No") -> No
A99: =Raw_Data!A99 -> C098 | B99: 37554 | C99: 22882 | D99: 20 | E99: 20% | F99: 7 | G99: 10 | H99: =IF(ISNUMBER(SEARCH("%",E99)), VALUE(SUBSTITUTE(E99,"%",""))/100, E99) -> 0.2 | I99: =IF(C99="", $J$2, C99) -> 22882 | K99: =IF(B99>PERCENTILE($B:$B,0.95),"Yes","No") -> No
A100: =Raw_Data!A100 -> C099 | B100: 40217 | C100: 26218 | D100: 11 | E100: 0.15 | F100: 5 | G100: 56 | H100: =IF(ISNUMBER(SEARCH("%",E100)), VALUE(SUBSTITUTE(E100,"%",""))/100, E100) -> 0.15 | I100: =IF(C100="", $J$2, C100) -> 26218 | K100: =IF(B100>PERCENTILE($B:$B,0.95),"Yes","No") -> No
...

Sheet Calculations
A1: Note: Cost_to_Serve includes fixed, operational, and overhead costs; hence may exceed revenue for some customers.(in comparison to revenue to cost)
A2: Customer_ID | B2: Revenue | C2: Cost_Clean | D2: Return_Rate_Clean | E2: Customer_Profit | F2: Revenue_Threshold | G2: Profit_Threshold | H2: Customer_Segment | I2: High Rev – Low Profit | J2: High Rev – High Profit
A3: =Clean_Data!A2 -> C001 | B3: =Clean_Data!B2 -> 2658 | C3: =Clean_Data!I2 -> 21973 | D3: =Clean_Data!H2 -> 0.22 | E3: =B3-C3 -> -19315 | F3: =PERCENTILE(B:B,0.75) -> 39153 | G3: =PERCENTILE(E:E,0.75) -> 22865 | H3: =IF(AND(B3>=$F$3, E3>=$G$3), "High Rev – High Profit", IF(AND(B3>=$F$3, E3<$G$3), "High Rev – Low Profit", IF(AND(B3<$F$3, E3>=$G$3), "Low Rev – High Profit", "Low Rev – Low Profit"))) -> Low Rev – Low Profit | I3: =COUNTIF(H:H,"High Rev – Low Profit") -> 15 | J3: =COUNTIF(H:H,"High Rev – High Profit") -> 35
A4: =Clean_Data!A3 -> C002 | B4: =Clean_Data!B3 -> 5103 | C4: =Clean_Data!I3 -> 14484 | D4: =Clean_Data!H3 -> 0.15 | E4: =B4-C4 -> -9381 | H4: =IF(AND(B4>=$F$3, E4>=$G$3), "High Rev – High Profit", IF(AND(B4>=$F$3, E4<$G$3), "High Rev – Low Profit", IF(AND(B4<$F$3, E4>=$G$3), "Low Rev – High Profit", "Low Rev – Low Profit"))) -> Low Rev – Low Profit
A5: =Clean_Data!A4 -> C003 | B5: =Clean_Data!B4 -> 25079 | C5: =Clean_Data!I4 -> 27280 | D5: =Clean_Data!H4 -> 0.18 | E5: =B5-C5 -> -2201 | H5: =IF(AND(B5>=$F$3, E5>=$G$3), "High Rev – High Profit", IF(AND(B5>=$F$3, E5<$G$3), "High Rev – Low Profit", IF(AND(B5<$F$3, E5>=$G$3), "Low Rev – High Profit", "Low Rev – Low Profit"))) -> Low Rev – Low Profit
A6: =Clean_Data!A5 -> C004 | B6: =Clean_Data!B5 -> 16960 | C6: =Clean_Data!I5 -> 26875 | D6: =Clean_Data!H5 -> 0.21 | E6: =B6-C6 -> -9915 | H6: =IF(AND(B6>=$F$3, E6>=$G$3), "High Rev – High Profit", IF(AND(B6>=$F$3, E6<$G$3), "High Rev – Low Profit", IF(AND(B6<$F$3, E6>=$G$3), "Low Rev – High Profit", "Low Rev – Low Profit"))) -> Low Rev – Low Profit
A7: =Clean_Data!A6 -> C005 | B7: =Clean_Data!B6 -> 30841 | C7: =Clean_Data!I6 -> 7986 | D7: =Clean_Data!H6 -> 0.12 | E7: =B7-C7 -> 22855 | H7: =IF(AND(B7>=$F$3, E7>=$G$3), "High Rev – High Profit", IF(AND(B7>=$F$3, E7<$G$3), "High Rev – Low Profit", IF(AND(B7<$F$3, E7>=$G$3), "Low Rev – High Profit", "Low Rev – Low Profit"))) -> Low Rev – Low Profit
A8: =Clean_Data!A7 -> C006 | B8: =Clean_Data!B7 -> 25139 | C8: =Clean_Data!I7 -> 19876 | D8: =Clean_Data!H7 -> 0.12 | E8: =B8-C8 -> 5263 | H8: =IF(AND(B8>=$F$3, E8>=$G$3), "High Rev – High Profit", IF(AND(B8>=$F$3, E8<$G$3), "High Rev – Low Profit", IF(AND(B8<$F$3, E8>=$G$3), "Low Rev – High Profit", "Low Rev – Low Profit"))) -> Low Rev – Low Profit
A9: =Clean_Data!A8 -> C007 | B9: =Clean_Data!B8 -> 11116 | C9: =Clean_Data!I8 -> 10808 | D9: =Clean_Data!H8 -> 0.25 | E9: =B9-C9 -> 308 | H9: =IF(AND(B9>=$F$3, E9>=$G$3), "High Rev – High Profit", IF(AND(B9>=$F$3, E9<$G$3), "High Rev – Low Profit", IF(AND(B9<$F$3, E9>=$G$3), "Low Rev – High Profit", "Low Rev – Low Profit"))) -> Low Rev – Low Profit
A10: =Clean_Data!A9 -> C008 | B10: =Clean_Data!B9 -> 44869 | C10: =Clean_Data!I9 -> 16868 | D10: =Clean_Data!H9 -> 0.24 | E10: =B10-C10 -> 28001 | H10: =IF(AND(B10>=$F$3, E10>=$G$3), "High Rev – High Profit", IF(AND(B10>=$F$3, E10<$G$3), "High Rev – Low Profit", IF(AND(B10<$F$3, E10>=$G$3), "Low Rev – High Profit", "Low Rev – Low Profit"))) -> High Rev – High Profit
A11: =Clean_Data!A10 -> C009 | B11: =Clean_Data!B10 -> 40105 | C11: =Clean_Data!I10 -> 2256 | D11: =Clean_Data!H10 -> 0.25 | E11: =B11-C11 -> 37849 | H11: =IF(AND(B11>=$F$3, E11>=$G$3), "High Rev – High Profit", IF(AND(B11>=$F$3, E11<$G$3), "High Rev – Low Profit", IF(AND(B11<$F$3, E11>=$G$3), "Low Rev – High Profit", "Low Rev – Low Profit"))) -> High Rev – High Profit
A12: =Clean_Data!A11 -> C010 | B12: =Clean_Data!B11 -> 48507 | C12: =Clean_Data!I11 -> 7943 | D12: =Clean_Data!H11 -> 0.17 | E12: =B12-C12 -> 40564 | H12: =IF(AND(B12>=$F$3, E12>=$G$3), "High Rev – High Profit", IF(AND(B12>=$F$3, E12<$G$3), "High Rev – Low Profit", IF(AND(B12<$F$3, E12>=$G$3), "Low Rev – High Profit", "Low Rev – Low Profit"))) -> High Rev – High Profit
A13: =Clean_Data!A12 -> C011 | B13: =Clean_Data!B12 -> 12530 | C13: =Clean_Data!I12 -> 23509 | E13: =B13-C13 -> -10979 | H13: =IF(AND(B13>=$F$3, E13>=$G$3), "High Rev – High Profit", IF(AND(B13>=$F$3, E13<$G$3), "High Rev – Low Profit", IF(AND(B13<$F$3, E13>=$G$3), "Low Rev – High Profit", "Low Rev – Low Profit"))) -> Low Rev – Low Profit
A14: =Clean_Data!A13 -> C012 | B14: =Clean_Data!B13 -> 13702 | C14: =Clean_Data!I13 -> 24076 | D14: =Clean_Data!H13 -> 0.06 | E14: =B14-C14 -> -10374 | H14: =IF(AND(B14>=$F$3, E14>=$G$3), "High Rev – High Profit", IF(AND(B14>=$F$3, E14<$G$3), "High Rev – Low Profit", IF(AND(B14<$F$3, E14>=$G$3), "Low Rev – High Profit", "Low Rev – Low Profit"))) -> Low Rev – Low Profit
A15: =Clean_Data!A14 -> C013 | B15: =Clean_Data!B14 -> 49946 | C15: =Clean_Data!I14 -> 22297 | D15: =Clean_Data!H14 -> 0.21 | E15: =B15-C15 -> 27649 | H15: =IF(AND(B15>=$F$3, E15>=$G$3), "High Rev – High Profit", IF(AND(B15>=$F$3, E15<$G$3), "High Rev – Low Profit", IF(AND(B15<$F$3, E15>=$G$3), "Low Rev – High Profit", "Low Rev – Low Profit"))) -> High Rev – High Profit
A16: =Clean_Data!A15 -> C014 | B16: =Clean_Data!B15 -> 2841 | C16: =Clean_Data!I15 -> 5160 | D16: =Clean_Data!H15 -> 0.14 | E16: =B16-C16 -> -2319 | H16: =IF(AND(B16>=$F$3, E16>=$G$3), "High Rev – High Profit", IF(AND(B16>=$F$3, E16<$G$3), "High Rev – Low Profit", IF(AND(B16<$F$3, E16>=$G$3), "Low Rev – High Profit", "Low Rev – Low Profit"))) -> Low Rev – Low Profit
A17: =Clean_Data!A16 -> C015 | B17: =Clean_Data!B16 -> 24430 | C17: =Clean_Data!I16 -> 19343 | D17: =Clean_Data!H16 -> 0.19 | E17: =B17-C17 -> 5087 | H17: =IF(AND(B17>=$F$3, E17>=$G$3), "High Rev – High Profit", IF(AND(B17>=$F$3, E17<$G$3), "High Rev – Low Profit", IF(AND(B17<$F$3, E17>=$G$3), "Low Rev – High Profit", "Low Rev – Low Profit"))) -> Low Rev – Low Profit
A18: =Clean_Data!A17 -> C016 | B18: =Clean_Data!B17 -> 43130 | C18: =Clean_Data!I17 -> 21994 | D18: =Clean_Data!H17 -> 0.13 | E18: =B18-C18 -> 21136 | H18: =IF(AND(B18>=$F$3, E18>=$G$3), "High Rev – High Profit", IF(AND(B18>=$F$3, E18<$G$3), "High Rev – Low Profit", IF(AND(B18<$F$3, E18>=$G$3), "Low Rev – High Profit", "Low Rev – Low Profit"))) -> High Rev – Low Profit
A19: =Clean_Data!A18 -> C017 | B19: =Clean_Data!B18 -> 41312 | C19: =Clean_Data!I18 -> 15974 | D19: =Clean_Data!H18 -> 0.13 | E19: =B19-C19 -> 25338 | H19: =IF(AND(B19>=$F$3, E19>=$G$3), "High Rev – High Profit", IF(AND(B19>=$F$3, E19<$G$3), "High Rev – Low Profit", IF(AND(B19<$F$3, E19>=$G$3), "Low Rev – High Profit", "Low Rev – Low Profit"))) -> High Rev – High Profit
A20: =Clean_Data!A19 -> C018 | B20: =Clean_Data!B19 -> 43466 | C20: =Clean_Data!I19 -> 19122 | D20: =Clean_Data!H19 -> 0.13 | E20: =B20-C20 -> 24344 | H20: =IF(AND(B20>=$F$3, E20>=$G$3), "High Rev – High Profit", IF(AND(B20>=$F$3, E20<$G$3), "High Rev – Low Profit", IF(AND(B20<$F$3, E20>=$G$3), "Low Rev – High Profit", "Low Rev – Low Profit"))) -> High Rev – High Profit
A21: =Clean_Data!A20 -> C019 | B21: =Clean_Data!B20 -> 6420 | C21: =Clean_Data!I20 -> 14730 | D21: =Clean_Data!H20 -> 0.02 | E21: =B21-C21 -> -8310 | H21: =IF(AND(B21>=$F$3, E21>=$G$3), "High Rev – High Profit", IF(AND(B21>=$F$3, E21<$G$3), "High Rev – Low Profit", IF(AND(B21<$F$3, E21>=$G$3), "Low Rev – High Profit", "Low Rev – Low Profit"))) -> Low Rev – Low Profit
A22: =Clean_Data!A21 -> C020 | B22: =Clean_Data!B21 -> 38243 | C22: =Clean_Data!I21 -> 7779 | D22: =Clean_Data!H21 -> 0.06 | E22: =B22-C22 -> 30464 | H22: =IF(AND(B22>=$F$3, E22>=$G$3), "High Rev – High Profit", IF(AND(B22>=$F$3, E22<$G$3), "High Rev – Low Profit", IF(AND(B22<$F$3, E22>=$G$3), "Low Rev – High Profit", "Low Rev – Low Profit"))) -> Low Rev – High Profit
A23: =Clean_Data!A22 -> C021 | B23: =Clean_Data!B22 -> 47981 | C23: =Clean_Data!I22 -> 12177 | D23: =Clean_Data!H22 -> 0.25 | E23: =B23-C23 -> 35804 | H23: =IF(AND(B23>=$F$3, E23>=$G$3), "High Rev – High Profit", IF(AND(B23>=$F$3, E23<$G$3), "High Rev – Low Profit", IF(AND(B23<$F$3, E23>=$G$3), "Low Rev – High Profit", "Low Rev – Low Profit"))) -> High Rev – High Profit
A24: =Clean_Data!A23 -> C022 | B24: =Clean_Data!B23 -> 48072 | C24: =Clean_Data!I23 -> 27827 | D24: =Clean_Data!H23 -> 0.3 | E24: =B24-C24 -> 20245 | H24: =IF(AND(B24>=$F$3, E24>=$G$3), "High Rev – High Profit", IF(AND(B24>=$F$3, E24<$G$3), "High Rev – Low Profit", IF(AND(B24<$F$3, E24>=$G$3), "Low Rev – High Profit", "Low Rev – Low Profit"))) -> High Rev – Low Profit
A25: =Clean_Data!A24 -> C023 | B25: =Clean_Data!B24 -> 2729 | C25: =Clean_Data!I24 -> 28066 | D25: =Clean_Data!H24 -> 0.18 | E25: =B25-C25 -> -25337 | H25: =IF(AND(B25>=$F$3, E25>=$G$3), "High Rev – High Profit", IF(AND(B25>=$F$3, E25<$G$3), "High Rev – Low Profit", IF(AND(B25<$F$3, E25>=$G$3), "Low Rev – High Profit", "Low Rev – Low Profit"))) -> Low Rev – Low Profit
... A202: =Clean_Data!A201 -> C200 | B202: =Clean_Data!B201 -> 29872 | C202: =Clean_Data!I201 -> 16653 | D202: =Clean_Data!H201 -> 0.02 | E202: =B202-C202 -> 13219 | H202: =IF(AND(B202>=$F$3, E202>=$G$3), "High Rev – High Profit", IF(AND(B202>=$F$3, E202<$G$3), "High Rev – Low Profit", IF(AND(B202<$F$3, E202>=$G$3), "Low Rev – High Profit", "Low Rev – Low Profit"))) -> Low Rev – Low Profit

Sheet Pivot_Revenue
A3: Row Labels | B3: Sum of Revenue
A4: High Rev – High Profit | B4: 1583998
A5: High Rev – Low Profit | B5: 662715
A6: Low Rev – High Profit | B6: 540939
A7: Low Rev – Low Profit | B7: 2598679
A8: Grand Total | B8: 5386331

Sheet Segment_Profit
A3: Row Labels | B3: Sum of Customer_Profit
A4: High Rev – High Profit | B4: 1078734
A5: High Rev – Low Profit | B5: 281767
A6: Low Rev – High Profit | B6: 403934
A7: Low Rev – Low Profit | B7: 332115
A8: Grand Total | B8: 2096550

Sheet Segment_Margin
A3: Row Labels | B3: Sum of Revenue | C3: Sum of Customer_Profit | D3: Sum of Margin
A4: High Rev – High Profit | B4: 1583998 | C4: 1078734 | D4: 0.6810198
A5: High Rev – Low Profit | B5: 662715 | C5: 281767 | D5: 0.4251707
A6: Low Rev – High Profit | B6: 540939 | C6: 403934 | D6: 0.74672745
A7: Low Rev – Low Profit | B7: 2598679 | C7: 332115 | D7: 0.12780147
A8: Grand Total | B8: 5386331 | C8: 2096550 | D8: 0.38923527

Sheet Segment_Actions
A1: Segment | B1: Key Insight | C1: Business Action
A2: High Rev – High Profit | B2: Core profit driver | C2: Retain, loyalty, premium support
A3: High Rev – Low Profit | B3: Revenue strong, margin weak | C3: Cost optimization, pricing review
A4: Low Rev – High Profit | B4: Highest efficiency | C4: Upsell, scale acquisition
A5: Low Rev – Low Profit | B5: High volume, low return | C5: Automate, prune, or reprice

Sheet Chart_Data
A1: Segment | B1: Revenue | C1: Margin | D1: Profit
A2: High Rev – High Profit | B2: 1583998 | C2: 0.681 | D2: 1078734
A3: High Rev – Low Profit | B3: 662715 | C3: 0.4252 | D3: 281767
A4: Low Rev – High Profit | B4: 540939 | C4: 0.7467 | D4: 403934
A5: Low Rev – Low Profit | B5: 2598679 | C5: 0.1278 | D5: 332115

Sheet Insights
A1: Segment 1: High Revenue – High Profit
A2: Insight: | B2: This segment contributes the highest share of total profit while also driving top-line revenue
A3: Business Meaning: | B3: These customers are the most efficient and valuable; pricing, costs, and return behavior are all working in the company’s favor.
A4: Action: | B4: Retain aggressively, avoid heavy discounting, and use this segment as the benchmark for defining the ideal customer profile.
A6: Segment 2: High Revenue – Low Profit
A7: Insight: | B7: Despite strong revenue, profitability is weak due to high costs, returns, or discounts.
A8: Business Meaning: | B8: Revenue alone is misleading here — this segment puts pressure on margins and operational efficiency.
A9: Action: | B9: Investigate cost drivers, tighten discount policies, reduce returns, or renegotiate pricing to restore profitability.
A11: Segment 3: Low Revenue – High Profit
A12: Insight: | B12: This segment delivers strong margins but contributes limited overall revenue.
A13: Business Meaning: | B13: These customers are efficient but under-scaled, indicating missed growth potential.
A14: Action: | B14: Target selectively for upselling and cross-selling to increase revenue without sacrificing margins.
A16: Segment 4: Low Revenue – Low Profit
A17: Insight: | B17: This segment generates minimal revenue and weak profitability, offering the least business value.
A18: Business Meaning: | B18: These customers consume resources without meaningful financial return.
A19: Action: | B19: Reduce service intensity, apply stricter pricing, or consider deprioritizing this segment altogether.

Sheet Dashboard
A1: Customer Revenue–Profit Segmentation Dashboard
B3: Updated:
B4: =TODAY() -> 46018
B5: Total Revenue | D5: Total Profit | F5: Avg Profit Margin | H5: Highest Profit Segment
B6: =SUM(Calculations!B:B) -> 5386331 | D6: =SUM(Calculations!E:E) -> 2096550 | F6: =AVERAGE(Calculations!F:F) -> 39153 | H6: High Revenue – High Profit
